regent/__init__.py
regent/constants.py
regent/debug.py
regent/exceptions.py
regent/socket.py
regent/client/__init__.py
regent/client/client.py
regent/service/__init__.py
regent/service/operation.py
regent/service/serialiser.py
regent/service/server.py
regent/service/storage.py
regent/service/auth/__init__.py
regent/service/auth/base.py
regent-0.1.0.dist-info/METADATA
regent-0.1.0.dist-info/WHEEL
regent-0.1.0.dist-info/top_level.txt
regent-0.1.0.dist-info/RECORD
