Metadata-Version: 2.1
Name: regent
Version: 0.1.0
Summary: Framework to allow untrusted users to perform privileged system tasks.
Home-page: https://radiac.net/projects/regent/
Author: Richard Terry
Author-email: code@radiac.net
License: BSD
Project-URL: Documentation, https://github.com/radiac/regent
Project-URL: Source, https://github.com/radiac/regent
Project-URL: Tracker, https://github.com/radiac/regent/issues
Keywords: sudo
Classifier: Development Status :: 5 - Production/Stable
Classifier: Environment :: Other Environment
Classifier: Intended Audience :: Developers
Classifier: License :: OSI Approved :: BSD License
Classifier: Operating System :: OS Independent
Classifier: Programming Language :: Python
Classifier: Programming Language :: Python :: 3
Classifier: Programming Language :: Python :: 3 :: Only
Classifier: Programming Language :: Python :: 3.6
Classifier: Programming Language :: Python :: 3.7
Classifier: Programming Language :: Python :: 3.8
Classifier: Programming Language :: Python :: 3.9
Classifier: Topic :: System :: Systems Administration
Requires-Python: >=3.6
